pyametista/README.rst
pyametista/__init__.py
pyametista/adapters/CSVAdapter.py
pyametista/adapters/DictAdapter.py
pyametista/adapters/MysqlAdapter.py
pyametista/adapters/PostgresqlAdapter.py
pyametista/adapters/__init__.py
pyametista/basic_report.py
pyametista/engine/__init__.py
pyametista/engine/bands/__init__.py
pyametista/engine/bands/bands.py
pyametista/engine/bands/elements.py
pyametista/engine/commonutilities.py
pyametista/engine/components/__init__.py
pyametista/engine/components/barcode.py
pyametista/engine/components/components.py
pyametista/engine/components/image.py
pyametista/engine/components/line.py
pyametista/engine/components/shapes.py
pyametista/engine/components/text.py
pyametista/engine/constants.py
pyametista/engine/jrxml2json.py
pyametista/engine/logging.json
pyametista/engine/reportGenerator.py
pyametista/exports/__init__.py
pyametista/exports/pdf.py
pyametista/fonts/LICENSE.txt
pyametista/fonts/OpenSans-Bold.ttf
pyametista/fonts/OpenSans-BoldItalic.ttf
pyametista/fonts/OpenSans-Italic.ttf
pyametista/fonts/OpenSans-Regular.ttf
pyametista/fonts/Roboto-Bold.ttf
pyametista/fonts/Roboto-BoldItalic.ttf
pyametista/fonts/Roboto-Italic.ttf
pyametista/fonts/Roboto-Regular.ttf
pyametista/fonts/RobotoSlab-Bold.ttf
pyametista/fonts/RobotoSlab-Regular.ttf
pyametista-0.1.8.dist-info/LICENSE
pyametista-0.1.8.dist-info/WHEEL
pyametista-0.1.8.dist-info/METADATA
pyametista-0.1.8.dist-info/RECORD
